{
  "deployments": [
    {
      "id": "b56d6c4a-6dd5-4d79-94ff-36370d245a35",
      "app_id": "625e727461d7b2000e5a1752",
      "created_at": "2022-07-18T15:59:06.024Z",
      "finished_at": "2022-07-18T16:04:29.166+00:00",
      "status": "success",
      "git_ref": "fbccee128921d38bceeae3d745d5b9cd562aee3d",
      "previous_git_ref": "2fa4ef13a3637cf51049598bcff88ba133fdab44",
      "type": "auto-deploy",
      "image": "registry-4-osc-fr1.scalingo.com/app-helios:fbccee128921d38-b56d6c4a-6dd5-4",
      "registry": "registry-4-osc-fr1.scalingo.com",
      "postdeploy_hook": "",
      "duration": 321,
      "pusher": {
        "username": "scalingo-platform-scm",
        "email": "deploy-scm@scalingo.com",
        "id": "us-f1de35ea-6a6d-4a25-8414-e2b34f5f61af"
      },
      "links": {
        "output": "https://api-osc-fr1.scalingo.com/v1/apps/625e727461d7b2000e5a1752/deployments/b56d6c4a-6dd5-4d79-94ff-36370d245a35/output"
      }
    },
    {
      "id": "d8d77f3e-aae1-4ac7-9c58-51fb8083392d",
      "app_id": "625e727461d7b2000e5a1752",
      "created_at": "2022-07-18T14:37:38.971Z",
      "finished_at": "2022-07-18T14:43:53.533+00:00",
      "status": "success",
      "git_ref": "2fa4ef13a3637cf51049598bcff88ba133fdab44",
      "previous_git_ref": "cfec1d388aa8b12f2754f7651ec93232bd2eb559",
      "type": "auto-deploy",
      "image": "registry-4-osc-fr1.scalingo.com/app-helios:2fa4ef13a3637cf-d8d77f3e-aae1-4",
      "registry": "registry-4-osc-fr1.scalingo.com",
      "postdeploy_hook": "",
      "duration": 373,
      "pusher": {
        "username": "scalingo-platform-scm",
        "email": "deploy-scm@scalingo.com",
        "id": "us-f1de35ea-6a6d-4a25-8414-e2b34f5f61af"
      },
      "links": {
        "output": "https://api-osc-fr1.scalingo.com/v1/apps/625e727461d7b2000e5a1752/deployments/d8d77f3e-aae1-4ac7-9c58-51fb8083392d/output"
      }
    },
    {
      "id": "1ab32a1d-9770-4174-893e-eb08d4bd0502",
      "app_id": "625e727461d7b2000e5a1752",
      "created_at": "2022-07-15T14:37:17.000Z",
      "finished_at": "2022-07-15T14:42:29.298+00:00",
      "status": "success",
      "git_ref": "cfec1d388aa8b12f2754f7651ec93232bd2eb559",
      "previous_git_ref": "ea954d295e6315a8de6a5edf0863706118efa66e",
      "type": "auto-deploy",
      "image": "registry-4-osc-fr1.scalingo.com/app-helios:cfec1d388aa8b12-1ab32a1d-9770-4",
      "registry": "registry-4-osc-fr1.scalingo.com",
      "postdeploy_hook": "",
      "duration": 311,
      "pusher": {
        "username": "scalingo-platform-scm",
        "email": "deploy-scm@scalingo.com",
        "id": "us-f1de35ea-6a6d-4a25-8414-e2b34f5f61af"
      },
      "links": {
        "output": "https://api-osc-fr1.scalingo.com/v1/apps/625e727461d7b2000e5a1752/deployments/1ab32a1d-9770-4174-893e-eb08d4bd0502/output"
      }
    },
    {
      "id": "85d7a167-5031-40c6-bede-943a81b87970",
      "app_id": "625e727461d7b2000e5a1752",
      "created_at": "2022-07-15T14:11:27.329Z",
      "finished_at": "2022-07-15T14:16:52.903+00:00",
      "status": "success",
      "git_ref": "ea954d295e6315a8de6a5edf0863706118efa66e",
      "previous_git_ref": "8c53131fd90ba8ba6b3136a37d3a4294441d4f43",
      "type": "auto-deploy",
      "image": "registry-4-osc-fr1.scalingo.com/app-helios:ea954d295e6315a-85d7a167-5031-4",
      "registry": "registry-4-osc-fr1.scalingo.com",
      "postdeploy_hook": "",
      "duration": 325,
      "pusher": {
        "username": "scalingo-platform-scm",
        "email": "deploy-scm@scalingo.com",
        "id": "us-f1de35ea-6a6d-4a25-8414-e2b34f5f61af"
      },
      "links": {
        "output": "https://api-osc-fr1.scalingo.com/v1/apps/625e727461d7b2000e5a1752/deployments/85d7a167-5031-40c6-bede-943a81b87970/output"
      }
    },
    {
      "id": "ef897f3b-f8ee-425c-9b1b-3d83cc49faf1",
      "app_id": "625e727461d7b2000e5a1752",
      "created_at": "2022-07-13T14:40:39.126Z",
      "finished_at": "2022-07-13T14:47:57.786+00:00",
      "status": "success",
      "git_ref": "8c53131fd90ba8ba6b3136a37d3a4294441d4f43",
      "previous_git_ref": "2c1cd081dcb2890a71c96281bece22dfb9f1867f",
      "type": "auto-deploy",
      "image": "registry-4-osc-fr1.scalingo.com/app-helios:8c53131fd90ba8b-ef897f3b-f8ee-4",
      "registry": "registry-4-osc-fr1.scalingo.com",
      "postdeploy_hook": "",
      "duration": 438,
      "pusher": {
        "username": "scalingo-platform-scm",
        "email": "deploy-scm@scalingo.com",
        "id": "us-f1de35ea-6a6d-4a25-8414-e2b34f5f61af"
      },
      "links": {
        "output": "https://api-osc-fr1.scalingo.com/v1/apps/625e727461d7b2000e5a1752/deployments/ef897f3b-f8ee-425c-9b1b-3d83cc49faf1/output"
      }
    },
    {
      "id": "15b257af-4941-4262-a5b6-6db921d6361c",
      "app_id": "625e727461d7b2000e5a1752",
      "created_at": "2022-07-12T16:31:21.698Z",
      "finished_at": "2022-07-12T16:37:37.052+00:00",
      "status": "success",
      "git_ref": "2c1cd081dcb2890a71c96281bece22dfb9f1867f",
      "previous_git_ref": "57a86517c822da9b81d36f65a1a2715e6adfe61e",
      "type": "auto-deploy",
      "image": "registry-4-osc-fr1.scalingo.com/app-helios:2c1cd081dcb2890-15b257af-4941-4",
      "registry": "registry-4-osc-fr1.scalingo.com",
      "postdeploy_hook": "",
      "duration": 374,
      "pusher": {
        "username": "scalingo-platform-scm",
        "email": "deploy-scm@scalingo.com",
        "id": "us-f1de35ea-6a6d-4a25-8414-e2b34f5f61af"
      },
      "links": {
        "output": "https://api-osc-fr1.scalingo.com/v1/apps/625e727461d7b2000e5a1752/deployments/15b257af-4941-4262-a5b6-6db921d6361c/output"
      }
    },
    {
      "id": "9de62b4d-e93b-49c9-81c3-2b77dbe31de7",
      "app_id": "625e727461d7b2000e5a1752",
      "created_at": "2022-07-12T08:44:30.267Z",
      "finished_at": "2022-07-12T08:57:56.471+00:00",
      "status": "success",
      "git_ref": "57a86517c822da9b81d36f65a1a2715e6adfe61e",
      "previous_git_ref": "1090b80cbfd100cd0aea0e26314927a4aa1055c8",
      "type": "auto-deploy",
      "image": "registry-4-osc-fr1.scalingo.com/app-helios:57a86517c822da9-9de62b4d-e93b-4",
      "registry": "registry-4-osc-fr1.scalingo.com",
      "postdeploy_hook": "",
      "duration": 805,
      "pusher": {
        "username": "scalingo-platform-scm",
        "email": "deploy-scm@scalingo.com",
        "id": "us-f1de35ea-6a6d-4a25-8414-e2b34f5f61af"
      },
      "links": {
        "output": "https://api-osc-fr1.scalingo.com/v1/apps/625e727461d7b2000e5a1752/deployments/9de62b4d-e93b-49c9-81c3-2b77dbe31de7/output"
      }
    },
    {
      "id": "2ba7394c-993c-467e-a98c-26791aa8768b",
      "app_id": "625e727461d7b2000e5a1752",
      "created_at": "2022-07-11T09:31:45.818Z",
      "finished_at": "2022-07-11T09:37:38.581+00:00",
      "status": "success",
      "git_ref": "1090b80cbfd100cd0aea0e26314927a4aa1055c8",
      "previous_git_ref": "5236ac67363e94a7b75a9a7d1580ab1facd32d56",
      "type": "auto-deploy",
      "image": "registry-4-osc-fr1.scalingo.com/app-helios:1090b80cbfd100c-2ba7394c-993c-4",
      "registry": "registry-4-osc-fr1.scalingo.com",
      "postdeploy_hook": "",
      "duration": 352,
      "pusher": {
        "username": "scalingo-platform-scm",
        "email": "deploy-scm@scalingo.com",
        "id": "us-f1de35ea-6a6d-4a25-8414-e2b34f5f61af"
      },
      "links": {
        "output": "https://api-osc-fr1.scalingo.com/v1/apps/625e727461d7b2000e5a1752/deployments/2ba7394c-993c-467e-a98c-26791aa8768b/output"
      }
    },
    {
      "id": "6dbba982-ed8b-418c-8774-bbb25cc2ad2d",
      "app_id": "625e727461d7b2000e5a1752",
      "created_at": "2022-07-08T13:46:04.408Z",
      "finished_at": "2022-07-08T13:51:55.317+00:00",
      "status": "success",
      "git_ref": "5236ac67363e94a7b75a9a7d1580ab1facd32d56",
      "previous_git_ref": "a3c5c9927cd85255b7d9d9865b18c22f5c69126a",
      "type": "auto-deploy",
      "image": "registry-4-osc-fr1.scalingo.com/app-helios:5236ac67363e94a-6dbba982-ed8b-4",
      "registry": "registry-4-osc-fr1.scalingo.com",
      "postdeploy_hook": "",
      "duration": 350,
      "pusher": {
        "username": "scalingo-platform-scm",
        "email": "deploy-scm@scalingo.com",
        "id": "us-f1de35ea-6a6d-4a25-8414-e2b34f5f61af"
      },
      "links": {
        "output": "https://api-osc-fr1.scalingo.com/v1/apps/625e727461d7b2000e5a1752/deployments/6dbba982-ed8b-418c-8774-bbb25cc2ad2d/output"
      }
    },
    {
      "id": "2f64361f-1498-49e9-baa8-a897f4ed0525",
      "app_id": "625e727461d7b2000e5a1752",
      "created_at": "2022-07-08T08:42:44.354Z",
      "finished_at": "2022-07-08T08:49:53.255+00:00",
      "status": "success",
      "git_ref": "a3c5c9927cd85255b7d9d9865b18c22f5c69126a",
      "previous_git_ref": "79195a9f036166d1763b161973d5a68ab7890956",
      "type": "auto-deploy",
      "image": "registry-4-osc-fr1.scalingo.com/app-helios:a3c5c9927cd8525-2f64361f-1498-4",
      "registry": "registry-4-osc-fr1.scalingo.com",
      "postdeploy_hook": "",
      "duration": 428,
      "pusher": {
        "username": "scalingo-platform-scm",
        "email": "deploy-scm@scalingo.com",
        "id": "us-f1de35ea-6a6d-4a25-8414-e2b34f5f61af"
      },
      "links": {
        "output": "https://api-osc-fr1.scalingo.com/v1/apps/625e727461d7b2000e5a1752/deployments/2f64361f-1498-49e9-baa8-a897f4ed0525/output"
      }
    },
    {
      "id": "ffe20b86-bd16-49fa-8738-2507dc70b0d4",
      "app_id": "625e727461d7b2000e5a1752",
      "created_at": "2022-07-07T15:28:17.156Z",
      "finished_at": "2022-07-07T15:35:02.572+00:00",
      "status": "success",
      "git_ref": "79195a9f036166d1763b161973d5a68ab7890956",
      "previous_git_ref": "a6a9feebf2cfafc54168f377892830b79003e2c2",
      "type": "auto-deploy",
      "image": "registry-4-osc-fr1.scalingo.com/app-helios:79195a9f036166d-ffe20b86-bd16-4",
      "registry": "registry-4-osc-fr1.scalingo.com",
      "postdeploy_hook": "",
      "duration": 404,
      "pusher": {
        "username": "scalingo-platform-scm",
        "email": "deploy-scm@scalingo.com",
        "id": "us-f1de35ea-6a6d-4a25-8414-e2b34f5f61af"
      },
      "links": {
        "output": "https://api-osc-fr1.scalingo.com/v1/apps/625e727461d7b2000e5a1752/deployments/ffe20b86-bd16-49fa-8738-2507dc70b0d4/output"
      }
    },
    {
      "id": "71a3d1f7-29b9-41af-a6fd-7e97a27c92e3",
      "app_id": "625e727461d7b2000e5a1752",
      "created_at": "2022-07-07T14:22:51.726Z",
      "finished_at": "2022-07-07T14:29:20.011+00:00",
      "status": "success",
      "git_ref": "a6a9feebf2cfafc54168f377892830b79003e2c2",
      "previous_git_ref": "1bbac6a7cbc31d58d53074f7446d725de898686f",
      "type": "auto-deploy",
      "image": "registry-4-osc-fr1.scalingo.com/app-helios:a6a9feebf2cfafc-71a3d1f7-29b9-4",
      "registry": "registry-4-osc-fr1.scalingo.com",
      "postdeploy_hook": "",
      "duration": 387,
      "pusher": {
        "username": "scalingo-platform-scm",
        "email": "deploy-scm@scalingo.com",
        "id": "us-f1de35ea-6a6d-4a25-8414-e2b34f5f61af"
      },
      "links": {
        "output": "https://api-osc-fr1.scalingo.com/v1/apps/625e727461d7b2000e5a1752/deployments/71a3d1f7-29b9-41af-a6fd-7e97a27c92e3/output"
      }
    },
    {
      "id": "8b33110a-8078-4f5a-a263-828a44db77c5",
      "app_id": "625e727461d7b2000e5a1752",
      "created_at": "2022-07-07T08:48:36.662Z",
      "finished_at": "2022-07-07T08:57:05.319+00:00",
      "status": "success",
      "git_ref": "1bbac6a7cbc31d58d53074f7446d725de898686f",
      "previous_git_ref": "cc3e851b9c1b0a7408582a7f948170bc4a7a1ff1",
      "type": "auto-deploy",
      "image": "registry-4-osc-fr1.scalingo.com/app-helios:1bbac6a7cbc31d5-8b33110a-8078-4",
      "registry": "registry-4-osc-fr1.scalingo.com",
      "postdeploy_hook": "",
      "duration": 507,
      "pusher": {
        "username": "scalingo-platform-scm",
        "email": "deploy-scm@scalingo.com",
        "id": "us-f1de35ea-6a6d-4a25-8414-e2b34f5f61af"
      },
      "links": {
        "output": "https://api-osc-fr1.scalingo.com/v1/apps/625e727461d7b2000e5a1752/deployments/8b33110a-8078-4f5a-a263-828a44db77c5/output"
      }
    },
    {
      "id": "c345eb4b-4c97-4563-a918-3645ffaef3b1",
      "app_id": "625e727461d7b2000e5a1752",
      "created_at": "2022-07-06T13:57:00.232Z",
      "finished_at": "2022-07-06T14:03:01.257+00:00",
      "status": "success",
      "git_ref": "cc3e851b9c1b0a7408582a7f948170bc4a7a1ff1",
      "previous_git_ref": "c317867da015f5033bb4f0d0fcc66eb78a030a0c",
      "type": "auto-deploy",
      "image": "registry-4-osc-fr1.scalingo.com/app-helios:cc3e851b9c1b0a7-c345eb4b-4c97-4",
      "registry": "registry-4-osc-fr1.scalingo.com",
      "postdeploy_hook": "",
      "duration": 360,
      "pusher": {
        "username": "scalingo-platform-scm",
        "email": "deploy-scm@scalingo.com",
        "id": "us-f1de35ea-6a6d-4a25-8414-e2b34f5f61af"
      },
      "links": {
        "output": "https://api-osc-fr1.scalingo.com/v1/apps/625e727461d7b2000e5a1752/deployments/c345eb4b-4c97-4563-a918-3645ffaef3b1/output"
      }
    },
    {
      "id": "36cd5fd2-e846-4c01-bceb-9ba4b7f2db8f",
      "app_id": "625e727461d7b2000e5a1752",
      "created_at": "2022-07-06T08:46:04.913Z",
      "finished_at": "2022-07-06T08:54:13.249+00:00",
      "status": "success",
      "git_ref": "c317867da015f5033bb4f0d0fcc66eb78a030a0c",
      "previous_git_ref": "4cb2adbe06461bea1789024180b5561d8069f90f",
      "type": "auto-deploy",
      "image": "registry-4-osc-fr1.scalingo.com/app-helios:c317867da015f50-36cd5fd2-e846-4",
      "registry": "registry-4-osc-fr1.scalingo.com",
      "postdeploy_hook": "",
      "duration": 487,
      "pusher": {
        "username": "scalingo-platform-scm",
        "email": "deploy-scm@scalingo.com",
        "id": "us-f1de35ea-6a6d-4a25-8414-e2b34f5f61af"
      },
      "links": {
        "output": "https://api-osc-fr1.scalingo.com/v1/apps/625e727461d7b2000e5a1752/deployments/36cd5fd2-e846-4c01-bceb-9ba4b7f2db8f/output"
      }
    },
    {
      "id": "9afa190e-14b6-4d37-9cb0-8fb1d116cef5",
      "app_id": "625e727461d7b2000e5a1752",
      "created_at": "2022-07-05T16:29:20.492Z",
      "finished_at": "2022-07-05T16:42:30.772+00:00",
      "status": "success",
      "git_ref": "4cb2adbe06461bea1789024180b5561d8069f90f",
      "previous_git_ref": "c3e893aadde45f5b4216fcc4264c2bc9adb2609e",
      "type": "auto-deploy",
      "image": "registry-4-osc-fr1.scalingo.com/app-helios:4cb2adbe06461be-9afa190e-14b6-4",
      "registry": "registry-4-osc-fr1.scalingo.com",
      "postdeploy_hook": "",
      "duration": 789,
      "pusher": {
        "username": "scalingo-platform-scm",
        "email": "deploy-scm@scalingo.com",
        "id": "us-f1de35ea-6a6d-4a25-8414-e2b34f5f61af"
      },
      "links": {
        "output": "https://api-osc-fr1.scalingo.com/v1/apps/625e727461d7b2000e5a1752/deployments/9afa190e-14b6-4d37-9cb0-8fb1d116cef5/output"
      }
    },
    {
      "id": "2f647ab9-adae-4b5a-9ad0-bddfa30dda25",
      "app_id": "625e727461d7b2000e5a1752",
      "created_at": "2022-07-05T15:17:52.306Z",
      "finished_at": "2022-07-05T15:24:09.339+00:00",
      "status": "success",
      "git_ref": "c3e893aadde45f5b4216fcc4264c2bc9adb2609e",
      "previous_git_ref": "24bd415ebff7fc046409c191be5fc090cc7a56b5",
      "type": "auto-deploy",
      "image": "registry-4-osc-fr1.scalingo.com/app-helios:c3e893aadde45f5-2f647ab9-adae-4",
      "registry": "registry-4-osc-fr1.scalingo.com",
      "postdeploy_hook": "",
      "duration": 376,
      "pusher": {
        "username": "scalingo-platform-scm",
        "email": "deploy-scm@scalingo.com",
        "id": "us-f1de35ea-6a6d-4a25-8414-e2b34f5f61af"
      },
      "links": {
        "output": "https://api-osc-fr1.scalingo.com/v1/apps/625e727461d7b2000e5a1752/deployments/2f647ab9-adae-4b5a-9ad0-bddfa30dda25/output"
      }
    },
    {
      "id": "a1a40c5b-23ee-412f-bc48-2b1ad67a5775",
      "app_id": "625e727461d7b2000e5a1752",
      "created_at": "2022-07-05T13:38:43.496Z",
      "finished_at": "2022-07-05T13:45:58.578+00:00",
      "status": "success",
      "git_ref": "24bd415ebff7fc046409c191be5fc090cc7a56b5",
      "previous_git_ref": "88634409057e4544cb090ba27222ca83473d6a71",
      "type": "auto-deploy",
      "image": "registry-4-osc-fr1.scalingo.com/app-helios:24bd415ebff7fc0-a1a40c5b-23ee-4",
      "registry": "registry-4-osc-fr1.scalingo.com",
      "postdeploy_hook": "",
      "duration": 434,
      "pusher": {
        "username": "scalingo-platform-scm",
        "email": "deploy-scm@scalingo.com",
        "id": "us-f1de35ea-6a6d-4a25-8414-e2b34f5f61af"
      },
      "links": {
        "output": "https://api-osc-fr1.scalingo.com/v1/apps/625e727461d7b2000e5a1752/deployments/a1a40c5b-23ee-412f-bc48-2b1ad67a5775/output"
      }
    },
    {
      "id": "49ff3a28-b1fe-475d-88b6-cb49e3238962",
      "app_id": "625e727461d7b2000e5a1752",
      "created_at": "2022-07-04T14:12:13.397Z",
      "finished_at": "2022-07-04T14:24:49.958+00:00",
      "status": "success",
      "git_ref": "88634409057e4544cb090ba27222ca83473d6a71",
      "previous_git_ref": "9a0374aa9fbbc81e5c9635cbe4d52385b81d1708",
      "type": "auto-deploy",
      "image": "registry-4-osc-fr1.scalingo.com/app-helios:88634409057e454-49ff3a28-b1fe-4",
      "registry": "registry-4-osc-fr1.scalingo.com",
      "postdeploy_hook": "",
      "duration": 756,
      "pusher": {
        "username": "scalingo-platform-scm",
        "email": "deploy-scm@scalingo.com",
        "id": "us-f1de35ea-6a6d-4a25-8414-e2b34f5f61af"
      },
      "links": {
        "output": "https://api-osc-fr1.scalingo.com/v1/apps/625e727461d7b2000e5a1752/deployments/49ff3a28-b1fe-475d-88b6-cb49e3238962/output"
      }
    },
    {
      "id": "d36b774c-875b-4e9f-8068-ad77ead14720",
      "app_id": "625e727461d7b2000e5a1752",
      "created_at": "2022-07-04T08:01:15.623Z",
      "finished_at": "2022-07-04T08:10:55.155+00:00",
      "status": "success",
      "git_ref": "9a0374aa9fbbc81e5c9635cbe4d52385b81d1708",
      "previous_git_ref": "2093560c64a468336413052104134deb08ba3e91",
      "type": "auto-deploy",
      "image": "registry-4-osc-fr1.scalingo.com/app-helios:9a0374aa9fbbc81-d36b774c-875b-4",
      "registry": "registry-4-osc-fr1.scalingo.com",
      "postdeploy_hook": "",
      "duration": 578,
      "pusher": {
        "username": "scalingo-platform-scm",
        "email": "deploy-scm@scalingo.com",
        "id": "us-f1de35ea-6a6d-4a25-8414-e2b34f5f61af"
      },
      "links": {
        "output": "https://api-osc-fr1.scalingo.com/v1/apps/625e727461d7b2000e5a1752/deployments/d36b774c-875b-4e9f-8068-ad77ead14720/output"
      }
    },
    {
      "id": "39ba8520-4382-469c-b622-e4bd98f48ced",
      "app_id": "625e727461d7b2000e5a1752",
      "created_at": "2022-07-01T15:34:16.869Z",
      "finished_at": "2022-07-01T15:49:11.436+00:00",
      "status": "success",
      "git_ref": "2093560c64a468336413052104134deb08ba3e91",
      "previous_git_ref": "2311b056553861c0a9b0f633da97f37267d77b38",
      "type": "auto-deploy",
      "image": "registry-4-osc-fr1.scalingo.com/app-helios:2093560c64a4683-39ba8520-4382-4",
      "registry": "registry-4-osc-fr1.scalingo.com",
      "postdeploy_hook": "",
      "duration": 894,
      "pusher": {
        "username": "scalingo-platform-scm",
        "email": "deploy-scm@scalingo.com",
        "id": "us-f1de35ea-6a6d-4a25-8414-e2b34f5f61af"
      },
      "links": {
        "output": "https://api-osc-fr1.scalingo.com/v1/apps/625e727461d7b2000e5a1752/deployments/39ba8520-4382-469c-b622-e4bd98f48ced/output"
      }
    },
    {
      "id": "09b275f3-9679-42c7-9233-dcc400a3d8ab",
      "app_id": "625e727461d7b2000e5a1752",
      "created_at": "2022-07-01T12:26:24.606Z",
      "finished_at": "2022-07-01T12:32:48.755+00:00",
      "status": "success",
      "git_ref": "2311b056553861c0a9b0f633da97f37267d77b38",
      "previous_git_ref": "24f10fe1d836ed06f48183f60ab44b0c45ad2462",
      "type": "auto-deploy",
      "image": "registry-4-osc-fr1.scalingo.com/app-helios:2311b056553861c-09b275f3-9679-4",
      "registry": "registry-4-osc-fr1.scalingo.com",
      "postdeploy_hook": "",
      "duration": 383,
      "pusher": {
        "username": "scalingo-platform-scm",
        "email": "deploy-scm@scalingo.com",
        "id": "us-f1de35ea-6a6d-4a25-8414-e2b34f5f61af"
      },
      "links": {
        "output": "https://api-osc-fr1.scalingo.com/v1/apps/625e727461d7b2000e5a1752/deployments/09b275f3-9679-42c7-9233-dcc400a3d8ab/output"
      }
    },
    {
      "id": "89c6e80c-836e-4e0d-b1db-80aee629b556",
      "app_id": "625e727461d7b2000e5a1752",
      "created_at": "2022-07-01T09:58:53.221Z",
      "finished_at": "2022-07-01T10:04:55.949+00:00",
      "status": "success",
      "git_ref": "24f10fe1d836ed06f48183f60ab44b0c45ad2462",
      "previous_git_ref": "7c207b85a49eae6b1b645db77f61e90c0a2247b2",
      "type": "auto-deploy",
      "image": "registry-4-osc-fr1.scalingo.com/app-helios:24f10fe1d836ed0-89c6e80c-836e-4",
      "registry": "registry-4-osc-fr1.scalingo.com",
      "postdeploy_hook": "",
      "duration": 361,
      "pusher": {
        "username": "scalingo-platform-scm",
        "email": "deploy-scm@scalingo.com",
        "id": "us-f1de35ea-6a6d-4a25-8414-e2b34f5f61af"
      },
      "links": {
        "output": "https://api-osc-fr1.scalingo.com/v1/apps/625e727461d7b2000e5a1752/deployments/89c6e80c-836e-4e0d-b1db-80aee629b556/output"
      }
    },
    {
      "id": "13724e36-bd86-4105-bc7d-0ee380db313d",
      "app_id": "625e727461d7b2000e5a1752",
      "created_at": "2022-07-01T08:53:18.836Z",
      "finished_at": "2022-07-01T09:08:43.614+00:00",
      "status": "success",
      "git_ref": "7c207b85a49eae6b1b645db77f61e90c0a2247b2",
      "previous_git_ref": "a28fc2de960ba82e69adc0ee998d2a33fb139ab8",
      "type": "auto-deploy",
      "image": "registry-4-osc-fr1.scalingo.com/app-helios:7c207b85a49eae6-13724e36-bd86-4",
      "registry": "registry-4-osc-fr1.scalingo.com",
      "postdeploy_hook": "",
      "duration": 924,
      "pusher": {
        "username": "scalingo-platform-scm",
        "email": "deploy-scm@scalingo.com",
        "id": "us-f1de35ea-6a6d-4a25-8414-e2b34f5f61af"
      },
      "links": {
        "output": "https://api-osc-fr1.scalingo.com/v1/apps/625e727461d7b2000e5a1752/deployments/13724e36-bd86-4105-bc7d-0ee380db313d/output"
      }
    },
    {
      "id": "a54db95f-ab92-4482-8bc3-be546294001f",
      "app_id": "625e727461d7b2000e5a1752",
      "created_at": "2022-06-30T08:27:40.515Z",
      "finished_at": "2022-06-30T08:33:03.513+00:00",
      "status": "success",
      "git_ref": "a28fc2de960ba82e69adc0ee998d2a33fb139ab8",
      "previous_git_ref": "101906e653d76c16e6341990dbda83d0bf4ef8ae",
      "type": "auto-deploy",
      "image": "registry-4-osc-fr1.scalingo.com/app-helios:a28fc2de960ba82-a54db95f-ab92-4",
      "registry": "registry-4-osc-fr1.scalingo.com",
      "postdeploy_hook": "",
      "duration": 322,
      "pusher": {
        "username": "scalingo-platform-scm",
        "email": "deploy-scm@scalingo.com",
        "id": "us-f1de35ea-6a6d-4a25-8414-e2b34f5f61af"
      },
      "links": {
        "output": "https://api-osc-fr1.scalingo.com/v1/apps/625e727461d7b2000e5a1752/deployments/a54db95f-ab92-4482-8bc3-be546294001f/output"
      }
    },
    {
      "id": "e373a381-ce09-41be-b6c5-80f2780cf480",
      "app_id": "625e727461d7b2000e5a1752",
      "created_at": "2022-06-30T08:09:23.062Z",
      "finished_at": "2022-06-30T08:23:33.280+00:00",
      "status": "success",
      "git_ref": "101906e653d76c16e6341990dbda83d0bf4ef8ae",
      "previous_git_ref": "db1bc42dd30dd7a891e0aa2790411dde495014a5",
      "type": "auto-deploy",
      "image": "registry-4-osc-fr1.scalingo.com/app-helios:101906e653d76c1-e373a381-ce09-4",
      "registry": "registry-4-osc-fr1.scalingo.com",
      "postdeploy_hook": "",
      "duration": 849,
      "pusher": {
        "username": "scalingo-platform-scm",
        "email": "deploy-scm@scalingo.com",
        "id": "us-f1de35ea-6a6d-4a25-8414-e2b34f5f61af"
      },
      "links": {
        "output": "https://api-osc-fr1.scalingo.com/v1/apps/625e727461d7b2000e5a1752/deployments/e373a381-ce09-41be-b6c5-80f2780cf480/output"
      }
    },
    {
      "id": "361b2a89-00cb-45fa-8618-6282c56efb86",
      "app_id": "625e727461d7b2000e5a1752",
      "created_at": "2022-06-29T16:19:14.389Z",
      "finished_at": "2022-06-29T16:32:11.817+00:00",
      "status": "success",
      "git_ref": "db1bc42dd30dd7a891e0aa2790411dde495014a5",
      "previous_git_ref": "486bbbc6220f37aeaf02f960fb745f44efbeefe9",
      "type": "auto-deploy",
      "image": "registry-4-osc-fr1.scalingo.com/app-helios:db1bc42dd30dd7a-361b2a89-00cb-4",
      "registry": "registry-4-osc-fr1.scalingo.com",
      "postdeploy_hook": "",
      "duration": 776,
      "pusher": {
        "username": "scalingo-platform-scm",
        "email": "deploy-scm@scalingo.com",
        "id": "us-f1de35ea-6a6d-4a25-8414-e2b34f5f61af"
      },
      "links": {
        "output": "https://api-osc-fr1.scalingo.com/v1/apps/625e727461d7b2000e5a1752/deployments/361b2a89-00cb-45fa-8618-6282c56efb86/output"
      }
    },
    {
      "id": "f6a7d2c4-d9ed-40f9-81fa-499b58051b77",
      "app_id": "625e727461d7b2000e5a1752",
      "created_at": "2022-06-27T14:45:06.566Z",
      "finished_at": "2022-06-27T14:46:28.763+00:00",
      "status": "build-error",
      "git_ref": "486bbbc6220f37aeaf02f960fb745f44efbeefe9",
      "previous_git_ref": "beeaeca8427bb3d587c351a447148d5449caa969",
      "type": "auto-deploy",
      "image": null,
      "registry": "registry-4-osc-fr1.scalingo.com",
      "postdeploy_hook": "",
      "duration": 0,
      "pusher": {
        "username": "scalingo-platform-scm",
        "email": "deploy-scm@scalingo.com",
        "id": "us-f1de35ea-6a6d-4a25-8414-e2b34f5f61af"
      },
      "links": {
        "output": "https://api-osc-fr1.scalingo.com/v1/apps/625e727461d7b2000e5a1752/deployments/f6a7d2c4-d9ed-40f9-81fa-499b58051b77/output"
      }
    },
    {
      "id": "f285059c-edbe-4099-8bab-cf3d1f1abf2d",
      "app_id": "625e727461d7b2000e5a1752",
      "created_at": "2022-06-27T14:08:22.694Z",
      "finished_at": "2022-06-27T14:21:33.944+00:00",
      "status": "success",
      "git_ref": "beeaeca8427bb3d587c351a447148d5449caa969",
      "previous_git_ref": "804c09fccfd60c6310572fbca01e46ac4f165a1c",
      "type": "auto-deploy",
      "image": "registry-4-osc-fr1.scalingo.com/app-helios:beeaeca8427bb3d-f285059c-edbe-4",
      "registry": "registry-4-osc-fr1.scalingo.com",
      "postdeploy_hook": "",
      "duration": 789,
      "pusher": {
        "username": "scalingo-platform-scm",
        "email": "deploy-scm@scalingo.com",
        "id": "us-f1de35ea-6a6d-4a25-8414-e2b34f5f61af"
      },
      "links": {
        "output": "https://api-osc-fr1.scalingo.com/v1/apps/625e727461d7b2000e5a1752/deployments/f285059c-edbe-4099-8bab-cf3d1f1abf2d/output"
      }
    },
    {
      "id": "bbbf3a83-8bf0-44ba-b55d-afd61744ceb1",
      "app_id": "625e727461d7b2000e5a1752",
      "created_at": "2022-06-27T08:36:34.679Z",
      "finished_at": "2022-06-27T08:44:18.654+00:00",
      "status": "success",
      "git_ref": "804c09fccfd60c6310572fbca01e46ac4f165a1c",
      "previous_git_ref": "fa660d8686e4e5f1003e161083861528eba8f7fa",
      "type": "auto-deploy",
      "image": "registry-4-osc-fr1.scalingo.com/app-helios:804c09fccfd60c6-bbbf3a83-8bf0-4",
      "registry": "registry-4-osc-fr1.scalingo.com",
      "postdeploy_hook": "",
      "duration": 463,
      "pusher": {
        "username": "scalingo-platform-scm",
        "email": "deploy-scm@scalingo.com",
        "id": "us-f1de35ea-6a6d-4a25-8414-e2b34f5f61af"
      },
      "links": {
        "output": "https://api-osc-fr1.scalingo.com/v1/apps/625e727461d7b2000e5a1752/deployments/bbbf3a83-8bf0-44ba-b55d-afd61744ceb1/output"
      }
    },
    {
      "id": "ec073f8e-181e-4677-95c4-7c2b15ce1bf6",
      "app_id": "625e727461d7b2000e5a1752",
      "created_at": "2022-06-27T07:29:57.904Z",
      "finished_at": "2022-06-27T07:35:53.624+00:00",
      "status": "success",
      "git_ref": "fa660d8686e4e5f1003e161083861528eba8f7fa",
      "previous_git_ref": "dee5830fd0eb154b10153fa48867dd70e8c363c6",
      "type": "auto-deploy",
      "image": "registry-4-osc-fr1.scalingo.com/app-helios:fa660d8686e4e5f-ec073f8e-181e-4",
      "registry": "registry-4-osc-fr1.scalingo.com",
      "postdeploy_hook": "",
      "duration": 355,
      "pusher": {
        "username": "scalingo-platform-scm",
        "email": "deploy-scm@scalingo.com",
        "id": "us-f1de35ea-6a6d-4a25-8414-e2b34f5f61af"
      },
      "links": {
        "output": "https://api-osc-fr1.scalingo.com/v1/apps/625e727461d7b2000e5a1752/deployments/ec073f8e-181e-4677-95c4-7c2b15ce1bf6/output"
      }
    },
    {
      "id": "d5927a1c-af0a-4927-b72c-6408b7228503",
      "app_id": "625e727461d7b2000e5a1752",
      "created_at": "2022-06-23T15:36:04.148Z",
      "finished_at": "2022-06-23T15:42:00.463+00:00",
      "status": "success",
      "git_ref": "dee5830fd0eb154b10153fa48867dd70e8c363c6",
      "previous_git_ref": "7da81d34080cea14e6eb56713443c21abe2c37c1",
      "type": "auto-deploy",
      "image": "registry-4-osc-fr1.scalingo.com/app-helios:dee5830fd0eb154-d5927a1c-af0a-4",
      "registry": "registry-4-osc-fr1.scalingo.com",
      "postdeploy_hook": "",
      "duration": 355,
      "pusher": {
        "username": "scalingo-platform-scm",
        "email": "deploy-scm@scalingo.com",
        "id": "us-f1de35ea-6a6d-4a25-8414-e2b34f5f61af"
      },
      "links": {
        "output": "https://api-osc-fr1.scalingo.com/v1/apps/625e727461d7b2000e5a1752/deployments/d5927a1c-af0a-4927-b72c-6408b7228503/output"
      }
    },
    {
      "id": "c93f1cc5-a00e-45d7-91af-c1fcc793c5ad",
      "app_id": "625e727461d7b2000e5a1752",
      "created_at": "2022-06-23T14:51:03.985Z",
      "finished_at": "2022-06-23T14:52:10.897+00:00",
      "status": "build-error",
      "git_ref": "7da81d34080cea14e6eb56713443c21abe2c37c1",
      "previous_git_ref": "06dd26ba4185c020ea41c8618607b2b8bededb5c",
      "type": "auto-deploy",
      "image": null,
      "registry": "registry-4-osc-fr1.scalingo.com",
      "postdeploy_hook": "",
      "duration": 0,
      "pusher": {
        "username": "scalingo-platform-scm",
        "email": "deploy-scm@scalingo.com",
        "id": "us-f1de35ea-6a6d-4a25-8414-e2b34f5f61af"
      },
      "links": {
        "output": "https://api-osc-fr1.scalingo.com/v1/apps/625e727461d7b2000e5a1752/deployments/c93f1cc5-a00e-45d7-91af-c1fcc793c5ad/output"
      }
    },
    {
      "id": "a188ce10-cce7-46cc-8a9a-283c90c8847b",
      "app_id": "625e727461d7b2000e5a1752",
      "created_at": "2022-06-23T13:43:15.807Z",
      "finished_at": "2022-06-23T13:54:17.787+00:00",
      "status": "success",
      "git_ref": "06dd26ba4185c020ea41c8618607b2b8bededb5c",
      "previous_git_ref": "bc6c0a2401e96913f060f0d151aad3563e74c2cc",
      "type": "auto-deploy",
      "image": "registry-4-osc-fr1.scalingo.com/app-helios:06dd26ba4185c02-a188ce10-cce7-4",
      "registry": "registry-4-osc-fr1.scalingo.com",
      "postdeploy_hook": "",
      "duration": 661,
      "pusher": {
        "username": "scalingo-platform-scm",
        "email": "deploy-scm@scalingo.com",
        "id": "us-f1de35ea-6a6d-4a25-8414-e2b34f5f61af"
      },
      "links": {
        "output": "https://api-osc-fr1.scalingo.com/v1/apps/625e727461d7b2000e5a1752/deployments/a188ce10-cce7-46cc-8a9a-283c90c8847b/output"
      }
    },
    {
      "id": "c668eac8-58e7-493b-a4f9-bbb9750bc263",
      "app_id": "625e727461d7b2000e5a1752",
      "created_at": "2022-06-22T14:10:32.791Z",
      "finished_at": "2022-06-22T14:18:38.851+00:00",
      "status": "success",
      "git_ref": "bc6c0a2401e96913f060f0d151aad3563e74c2cc",
      "previous_git_ref": "8da3760dba821f0864c8fe099dfd20b3e10b6579",
      "type": "auto-deploy",
      "image": "registry-4-osc-fr1.scalingo.com/app-helios:bc6c0a2401e9691-c668eac8-58e7-4",
      "registry": "registry-4-osc-fr1.scalingo.com",
      "postdeploy_hook": "",
      "duration": 485,
      "pusher": {
        "username": "scalingo-platform-scm",
        "email": "deploy-scm@scalingo.com",
        "id": "us-f1de35ea-6a6d-4a25-8414-e2b34f5f61af"
      },
      "links": {
        "output": "https://api-osc-fr1.scalingo.com/v1/apps/625e727461d7b2000e5a1752/deployments/c668eac8-58e7-493b-a4f9-bbb9750bc263/output"
      }
    },
    {
      "id": "bca50528-e7e7-4c53-9556-af2a01f3e06a",
      "app_id": "625e727461d7b2000e5a1752",
      "created_at": "2022-06-22T14:04:36.516Z",
      "finished_at": "2022-06-22T14:17:30.916+00:00",
      "status": "success",
      "git_ref": "8da3760dba821f0864c8fe099dfd20b3e10b6579",
      "previous_git_ref": "296ca0c7a8e476650ef3fbd63bd857467a001e31",
      "type": "auto-deploy",
      "image": "registry-4-osc-fr1.scalingo.com/app-helios:8da3760dba821f0-bca50528-e7e7-4",
      "registry": "registry-4-osc-fr1.scalingo.com",
      "postdeploy_hook": "",
      "duration": 773,
      "pusher": {
        "username": "scalingo-platform-scm",
        "email": "deploy-scm@scalingo.com",
        "id": "us-f1de35ea-6a6d-4a25-8414-e2b34f5f61af"
      },
      "links": {
        "output": "https://api-osc-fr1.scalingo.com/v1/apps/625e727461d7b2000e5a1752/deployments/bca50528-e7e7-4c53-9556-af2a01f3e06a/output"
      }
    },
    {
      "id": "483f13e5-4713-489a-bee1-17af01aaec11",
      "app_id": "625e727461d7b2000e5a1752",
      "created_at": "2022-06-21T11:43:14.071Z",
      "finished_at": "2022-06-21T11:50:52.467+00:00",
      "status": "success",
      "git_ref": "296ca0c7a8e476650ef3fbd63bd857467a001e31",
      "previous_git_ref": "62c2e53612655f702e998638ef59055418cf60ed",
      "type": "auto-deploy",
      "image": "registry-3-osc-fr1.scalingo.com/app-helios:296ca0c7a8e4766-483f13e5-4713-4",
      "registry": "registry-3-osc-fr1.scalingo.com",
      "postdeploy_hook": "",
      "duration": 457,
      "pusher": {
        "username": "scalingo-platform-scm",
        "email": "deploy-scm@scalingo.com",
        "id": "us-f1de35ea-6a6d-4a25-8414-e2b34f5f61af"
      },
      "links": {
        "output": "https://api-osc-fr1.scalingo.com/v1/apps/625e727461d7b2000e5a1752/deployments/483f13e5-4713-489a-bee1-17af01aaec11/output"
      }
    },
    {
      "id": "bcf35cbd-3f57-437f-bb00-57414567cb6d",
      "app_id": "625e727461d7b2000e5a1752",
      "created_at": "2022-06-21T08:48:24.556Z",
      "finished_at": "2022-06-21T08:55:29.290+00:00",
      "status": "success",
      "git_ref": "62c2e53612655f702e998638ef59055418cf60ed",
      "previous_git_ref": "2fd6336c48927327f578d269e657d34c3b089322",
      "type": "auto-deploy",
      "image": "registry-3-osc-fr1.scalingo.com/app-helios:62c2e53612655f7-bcf35cbd-3f57-4",
      "registry": "registry-3-osc-fr1.scalingo.com",
      "postdeploy_hook": "",
      "duration": 424,
      "pusher": {
        "username": "scalingo-platform-scm",
        "email": "deploy-scm@scalingo.com",
        "id": "us-f1de35ea-6a6d-4a25-8414-e2b34f5f61af"
      },
      "links": {
        "output": "https://api-osc-fr1.scalingo.com/v1/apps/625e727461d7b2000e5a1752/deployments/bcf35cbd-3f57-437f-bb00-57414567cb6d/output"
      }
    },
    {
      "id": "f7652457-e1a9-4a98-aad2-3fc59201ddd4",
      "app_id": "625e727461d7b2000e5a1752",
      "created_at": "2022-06-17T15:49:35.574Z",
      "finished_at": "2022-06-17T15:55:52.250+00:00",
      "status": "success",
      "git_ref": "2fd6336c48927327f578d269e657d34c3b089322",
      "previous_git_ref": "2c7a113901fe3f75df6d1fe7385262fddb4be71d",
      "type": "auto-deploy",
      "image": "registry-3-osc-fr1.scalingo.com/app-helios:2fd6336c4892732-f7652457-e1a9-4",
      "registry": "registry-3-osc-fr1.scalingo.com",
      "postdeploy_hook": "",
      "duration": 376,
      "pusher": {
        "username": "scalingo-platform-scm",
        "email": "deploy-scm@scalingo.com",
        "id": "us-f1de35ea-6a6d-4a25-8414-e2b34f5f61af"
      },
      "links": {
        "output": "https://api-osc-fr1.scalingo.com/v1/apps/625e727461d7b2000e5a1752/deployments/f7652457-e1a9-4a98-aad2-3fc59201ddd4/output"
      }
    },
    {
      "id": "1bb3fe2c-49f3-447b-a75a-72e36400b6e5",
      "app_id": "625e727461d7b2000e5a1752",
      "created_at": "2022-06-16T07:04:43.782Z",
      "finished_at": "2022-06-16T07:12:18.686+00:00",
      "status": "success",
      "git_ref": "2c7a113901fe3f75df6d1fe7385262fddb4be71d",
      "previous_git_ref": "4b31e363be5751f5dc5e7fcb3c0e427243f7389e",
      "type": "auto-deploy",
      "image": "registry-3-osc-fr1.scalingo.com/app-helios:2c7a113901fe3f7-1bb3fe2c-49f3-4",
      "registry": "registry-3-osc-fr1.scalingo.com",
      "postdeploy_hook": "",
      "duration": 454,
      "pusher": {
        "username": "scalingo-platform-scm",
        "email": "deploy-scm@scalingo.com",
        "id": "us-f1de35ea-6a6d-4a25-8414-e2b34f5f61af"
      },
      "links": {
        "output": "https://api-osc-fr1.scalingo.com/v1/apps/625e727461d7b2000e5a1752/deployments/1bb3fe2c-49f3-447b-a75a-72e36400b6e5/output"
      }
    },
    {
      "id": "72607dca-f8a8-4f6c-a827-50090715050c",
      "app_id": "625e727461d7b2000e5a1752",
      "created_at": "2022-06-15T15:37:41.765Z",
      "finished_at": "2022-06-15T15:46:40.176+00:00",
      "status": "success",
      "git_ref": "4b31e363be5751f5dc5e7fcb3c0e427243f7389e",
      "previous_git_ref": "b0fdaa35c079d74731678969df1235af840a5086",
      "type": "auto-deploy",
      "image": "registry-3-osc-fr1.scalingo.com/app-helios:4b31e363be5751f-72607dca-f8a8-4",
      "registry": "registry-3-osc-fr1.scalingo.com",
      "postdeploy_hook": "",
      "duration": 495,
      "pusher": {
        "username": "scalingo-platform-scm",
        "email": "deploy-scm@scalingo.com",
        "id": "us-f1de35ea-6a6d-4a25-8414-e2b34f5f61af"
      },
      "links": {
        "output": "https://api-osc-fr1.scalingo.com/v1/apps/625e727461d7b2000e5a1752/deployments/72607dca-f8a8-4f6c-a827-50090715050c/output"
      }
    },
    {
      "id": "966f30bc-b10a-40e8-8e48-3fe30933f4fa",
      "app_id": "625e727461d7b2000e5a1752",
      "created_at": "2022-06-15T13:02:33.150Z",
      "finished_at": "2022-06-15T13:10:54.596+00:00",
      "status": "success",
      "git_ref": "b0fdaa35c079d74731678969df1235af840a5086",
      "previous_git_ref": "8df5917e4949a9ccf5d8a1239830a081bb66a3a5",
      "type": "auto-deploy",
      "image": "registry-3-osc-fr1.scalingo.com/app-helios:b0fdaa35c079d74-966f30bc-b10a-4",
      "registry": "registry-3-osc-fr1.scalingo.com",
      "postdeploy_hook": "",
      "duration": 500,
      "pusher": {
        "username": "scalingo-platform-scm",
        "email": "deploy-scm@scalingo.com",
        "id": "us-f1de35ea-6a6d-4a25-8414-e2b34f5f61af"
      },
      "links": {
        "output": "https://api-osc-fr1.scalingo.com/v1/apps/625e727461d7b2000e5a1752/deployments/966f30bc-b10a-40e8-8e48-3fe30933f4fa/output"
      }
    },
    {
      "id": "e42bbf14-a5ff-46a1-9d57-d390022c9086",
      "app_id": "625e727461d7b2000e5a1752",
      "created_at": "2022-06-15T08:40:07.988Z",
      "finished_at": "2022-06-15T08:47:35.872+00:00",
      "status": "success",
      "git_ref": "8df5917e4949a9ccf5d8a1239830a081bb66a3a5",
      "previous_git_ref": "c7cce1ddfbae286e77aa9f82a4af33b6a928da93",
      "type": "auto-deploy",
      "image": "registry-3-osc-fr1.scalingo.com/app-helios:8df5917e4949a9c-e42bbf14-a5ff-4",
      "registry": "registry-3-osc-fr1.scalingo.com",
      "postdeploy_hook": "",
      "duration": 447,
      "pusher": {
        "username": "scalingo-platform-scm",
        "email": "deploy-scm@scalingo.com",
        "id": "us-f1de35ea-6a6d-4a25-8414-e2b34f5f61af"
      },
      "links": {
        "output": "https://api-osc-fr1.scalingo.com/v1/apps/625e727461d7b2000e5a1752/deployments/e42bbf14-a5ff-46a1-9d57-d390022c9086/output"
      }
    },
    {
      "id": "1bd4dd66-3eee-410e-98c2-5d371d85ddd7",
      "app_id": "625e727461d7b2000e5a1752",
      "created_at": "2022-06-14T15:28:30.874Z",
      "finished_at": "2022-06-14T15:34:51.899+00:00",
      "status": "success",
      "git_ref": "c7cce1ddfbae286e77aa9f82a4af33b6a928da93",
      "previous_git_ref": "36795f062d0a14ad59d6c5bac4680e9d2105284b",
      "type": "auto-deploy",
      "image": "registry-3-osc-fr1.scalingo.com/app-helios:c7cce1ddfbae286-1bd4dd66-3eee-4",
      "registry": "registry-3-osc-fr1.scalingo.com",
      "postdeploy_hook": "",
      "duration": 380,
      "pusher": {
        "username": "scalingo-platform-scm",
        "email": "deploy-scm@scalingo.com",
        "id": "us-f1de35ea-6a6d-4a25-8414-e2b34f5f61af"
      },
      "links": {
        "output": "https://api-osc-fr1.scalingo.com/v1/apps/625e727461d7b2000e5a1752/deployments/1bd4dd66-3eee-410e-98c2-5d371d85ddd7/output"
      }
    },
    {
      "id": "ff9c17e7-86fd-4386-ba27-b171b7c4f2e5",
      "app_id": "625e727461d7b2000e5a1752",
      "created_at": "2022-06-14T13:43:08.378Z",
      "finished_at": "2022-06-14T13:49:21.750+00:00",
      "status": "success",
      "git_ref": "36795f062d0a14ad59d6c5bac4680e9d2105284b",
      "previous_git_ref": "42a760cf0518f95e2cbcc5682a799cc575fba08f",
      "type": "auto-deploy",
      "image": "registry-3-osc-fr1.scalingo.com/app-helios:36795f062d0a14a-ff9c17e7-86fd-4",
      "registry": "registry-3-osc-fr1.scalingo.com",
      "postdeploy_hook": "",
      "duration": 372,
      "pusher": {
        "username": "scalingo-platform-scm",
        "email": "deploy-scm@scalingo.com",
        "id": "us-f1de35ea-6a6d-4a25-8414-e2b34f5f61af"
      },
      "links": {
        "output": "https://api-osc-fr1.scalingo.com/v1/apps/625e727461d7b2000e5a1752/deployments/ff9c17e7-86fd-4386-ba27-b171b7c4f2e5/output"
      }
    },
    {
      "id": "d5d89b17-1032-48be-aace-3b906a487da4",
      "app_id": "625e727461d7b2000e5a1752",
      "created_at": "2022-06-14T09:07:30.240Z",
      "finished_at": "2022-06-14T09:13:57.196+00:00",
      "status": "success",
      "git_ref": "42a760cf0518f95e2cbcc5682a799cc575fba08f",
      "previous_git_ref": "8d02f7d303609a9bd639ada8388edb3dc746d776",
      "type": "auto-deploy",
      "image": "registry-3-osc-fr1.scalingo.com/app-helios:42a760cf0518f95-d5d89b17-1032-4",
      "registry": "registry-3-osc-fr1.scalingo.com",
      "postdeploy_hook": "",
      "duration": 386,
      "pusher": {
        "username": "scalingo-platform-scm",
        "email": "deploy-scm@scalingo.com",
        "id": "us-f1de35ea-6a6d-4a25-8414-e2b34f5f61af"
      },
      "links": {
        "output": "https://api-osc-fr1.scalingo.com/v1/apps/625e727461d7b2000e5a1752/deployments/d5d89b17-1032-48be-aace-3b906a487da4/output"
      }
    },
    {
      "id": "2ba960c4-3209-4022-9bc1-75f2d84056fb",
      "app_id": "625e727461d7b2000e5a1752",
      "created_at": "2022-06-13T10:17:13.533Z",
      "finished_at": "2022-06-13T10:23:33.843+00:00",
      "status": "success",
      "git_ref": "8d02f7d303609a9bd639ada8388edb3dc746d776",
      "previous_git_ref": "984270079bc570235845560cd05b4dbd10245293",
      "type": "auto-deploy",
      "image": "registry-3-osc-fr1.scalingo.com/app-helios:8d02f7d303609a9-2ba960c4-3209-4",
      "registry": "registry-3-osc-fr1.scalingo.com",
      "postdeploy_hook": "",
      "duration": 379,
      "pusher": {
        "username": "scalingo-platform-scm",
        "email": "deploy-scm@scalingo.com",
        "id": "us-f1de35ea-6a6d-4a25-8414-e2b34f5f61af"
      },
      "links": {
        "output": "https://api-osc-fr1.scalingo.com/v1/apps/625e727461d7b2000e5a1752/deployments/2ba960c4-3209-4022-9bc1-75f2d84056fb/output"
      }
    },
    {
      "id": "2d0b0fc6-628b-40ec-8345-da56761e62cf",
      "app_id": "625e727461d7b2000e5a1752",
      "created_at": "2022-06-10T15:18:13.101Z",
      "finished_at": "2022-06-10T15:23:29.128+00:00",
      "status": "success",
      "git_ref": "984270079bc570235845560cd05b4dbd10245293",
      "previous_git_ref": "e099da62f5b9c0905f45b27bc13b6207ae998035",
      "type": "auto-deploy",
      "image": "registry-3-osc-fr1.scalingo.com/app-helios:984270079bc5702-2d0b0fc6-628b-4",
      "registry": "registry-3-osc-fr1.scalingo.com",
      "postdeploy_hook": "",
      "duration": 315,
      "pusher": {
        "username": "scalingo-platform-scm",
        "email": "deploy-scm@scalingo.com",
        "id": "us-f1de35ea-6a6d-4a25-8414-e2b34f5f61af"
      },
      "links": {
        "output": "https://api-osc-fr1.scalingo.com/v1/apps/625e727461d7b2000e5a1752/deployments/2d0b0fc6-628b-40ec-8345-da56761e62cf/output"
      }
    },
    {
      "id": "4c5bfe0e-f8c3-4778-afb5-c9c29d34c5ca",
      "app_id": "625e727461d7b2000e5a1752",
      "created_at": "2022-06-10T10:25:38.115Z",
      "finished_at": "2022-06-10T10:30:50.780+00:00",
      "status": "success",
      "git_ref": "e099da62f5b9c0905f45b27bc13b6207ae998035",
      "previous_git_ref": "1f4135171e158b96c5eeed572f060c6b52db3024",
      "type": "auto-deploy",
      "image": "registry-3-osc-fr1.scalingo.com/app-helios:e099da62f5b9c09-4c5bfe0e-f8c3-4",
      "registry": "registry-3-osc-fr1.scalingo.com",
      "postdeploy_hook": "",
      "duration": 312,
      "pusher": {
        "username": "scalingo-platform-scm",
        "email": "deploy-scm@scalingo.com",
        "id": "us-f1de35ea-6a6d-4a25-8414-e2b34f5f61af"
      },
      "links": {
        "output": "https://api-osc-fr1.scalingo.com/v1/apps/625e727461d7b2000e5a1752/deployments/4c5bfe0e-f8c3-4778-afb5-c9c29d34c5ca/output"
      }
    },
    {
      "id": "4b366482-5908-4e16-bbea-4dea4cff06c1",
      "app_id": "625e727461d7b2000e5a1752",
      "created_at": "2022-06-10T09:59:36.811Z",
      "finished_at": "2022-06-10T10:05:04.595+00:00",
      "status": "success",
      "git_ref": "1f4135171e158b96c5eeed572f060c6b52db3024",
      "previous_git_ref": "6afbef71030f2daa5118a3120c770b22e5a50ab2",
      "type": "auto-deploy",
      "image": "registry-3-osc-fr1.scalingo.com/app-helios:1f4135171e158b9-4b366482-5908-4",
      "registry": "registry-3-osc-fr1.scalingo.com",
      "postdeploy_hook": "",
      "duration": 326,
      "pusher": {
        "username": "scalingo-platform-scm",
        "email": "deploy-scm@scalingo.com",
        "id": "us-f1de35ea-6a6d-4a25-8414-e2b34f5f61af"
      },
      "links": {
        "output": "https://api-osc-fr1.scalingo.com/v1/apps/625e727461d7b2000e5a1752/deployments/4b366482-5908-4e16-bbea-4dea4cff06c1/output"
      }
    },
    {
      "id": "48183dbf-1232-4103-8216-062f8ad46cd9",
      "app_id": "625e727461d7b2000e5a1752",
      "created_at": "2022-06-09T13:03:17.295Z",
      "finished_at": "2022-06-09T13:15:26.848+00:00",
      "status": "success",
      "git_ref": "6afbef71030f2daa5118a3120c770b22e5a50ab2",
      "previous_git_ref": "acf178870907e13b72f38b2f6d4743c2178d5210",
      "type": "auto-deploy",
      "image": "registry-3-osc-fr1.scalingo.com/app-helios:6afbef71030f2da-48183dbf-1232-4",
      "registry": "registry-3-osc-fr1.scalingo.com",
      "postdeploy_hook": "",
      "duration": 729,
      "pusher": {
        "username": "scalingo-platform-scm",
        "email": "deploy-scm@scalingo.com",
        "id": "us-f1de35ea-6a6d-4a25-8414-e2b34f5f61af"
      },
      "links": {
        "output": "https://api-osc-fr1.scalingo.com/v1/apps/625e727461d7b2000e5a1752/deployments/48183dbf-1232-4103-8216-062f8ad46cd9/output"
      }
    },
    {
      "id": "f1d0da12-89e4-4890-9960-1b75d9cb4539",
      "app_id": "625e727461d7b2000e5a1752",
      "created_at": "2022-06-09T09:26:08.513Z",
      "finished_at": "2022-06-09T09:31:58.486+00:00",
      "status": "success",
      "git_ref": "acf178870907e13b72f38b2f6d4743c2178d5210",
      "previous_git_ref": "ebb9efb4a36feef39dc1c6fdc2847afa9663929a",
      "type": "auto-deploy",
      "image": "registry-3-osc-fr1.scalingo.com/app-helios:acf178870907e13-f1d0da12-89e4-4",
      "registry": "registry-3-osc-fr1.scalingo.com",
      "postdeploy_hook": "",
      "duration": 349,
      "pusher": {
        "username": "scalingo-platform-scm",
        "email": "deploy-scm@scalingo.com",
        "id": "us-f1de35ea-6a6d-4a25-8414-e2b34f5f61af"
      },
      "links": {
        "output": "https://api-osc-fr1.scalingo.com/v1/apps/625e727461d7b2000e5a1752/deployments/f1d0da12-89e4-4890-9960-1b75d9cb4539/output"
      }
    },
    {
      "id": "fd6dacbc-9f26-42c2-bf24-3d1bea3d8693",
      "app_id": "625e727461d7b2000e5a1752",
      "created_at": "2022-06-07T09:39:53.144Z",
      "finished_at": "2022-06-07T09:44:56.836+00:00",
      "status": "success",
      "git_ref": "ebb9efb4a36feef39dc1c6fdc2847afa9663929a",
      "previous_git_ref": "9cb3a6acc5cdd28ac90b9f154827c951bc4f943d",
      "type": "auto-deploy",
      "image": "registry-3-osc-fr1.scalingo.com/app-helios:ebb9efb4a36feef-fd6dacbc-9f26-4",
      "registry": "registry-3-osc-fr1.scalingo.com",
      "postdeploy_hook": "",
      "duration": 303,
      "pusher": {
        "username": "scalingo-platform-scm",
        "email": "deploy-scm@scalingo.com",
        "id": "us-f1de35ea-6a6d-4a25-8414-e2b34f5f61af"
      },
      "links": {
        "output": "https://api-osc-fr1.scalingo.com/v1/apps/625e727461d7b2000e5a1752/deployments/fd6dacbc-9f26-42c2-bf24-3d1bea3d8693/output"
      }
    },
    {
      "id": "89a90a7e-bad6-484e-80a9-77b07e65f04f",
      "app_id": "625e727461d7b2000e5a1752",
      "created_at": "2022-06-03T08:19:48.387Z",
      "finished_at": "2022-06-03T08:25:48.902+00:00",
      "status": "success",
      "git_ref": "9cb3a6acc5cdd28ac90b9f154827c951bc4f943d",
      "previous_git_ref": "dd13e5259188667f136d8ccb206095f1fcc08c17",
      "type": "auto-deploy",
      "image": "registry-3-osc-fr1.scalingo.com/app-helios:9cb3a6acc5cdd28-89a90a7e-bad6-4",
      "registry": "registry-3-osc-fr1.scalingo.com",
      "postdeploy_hook": "",
      "duration": 360,
      "pusher": {
        "username": "scalingo-platform-scm",
        "email": "deploy-scm@scalingo.com",
        "id": "us-f1de35ea-6a6d-4a25-8414-e2b34f5f61af"
      },
      "links": {
        "output": "https://api-osc-fr1.scalingo.com/v1/apps/625e727461d7b2000e5a1752/deployments/89a90a7e-bad6-484e-80a9-77b07e65f04f/output"
      }
    },
    {
      "id": "024810a3-d92c-4a1b-8244-8f1ff41b9ea0",
      "app_id": "625e727461d7b2000e5a1752",
      "created_at": "2022-06-02T13:21:47.801Z",
      "finished_at": "2022-06-02T13:25:34.779+00:00",
      "status": "success",
      "git_ref": "dd13e5259188667f136d8ccb206095f1fcc08c17",
      "previous_git_ref": "3ca80caad827b3813f5e582c9ba38908bd7f4887",
      "type": "auto-deploy",
      "image": "registry-3-osc-fr1.scalingo.com/app-helios:dd13e5259188667-024810a3-d92c-4",
      "registry": "registry-3-osc-fr1.scalingo.com",
      "postdeploy_hook": "",
      "duration": 226,
      "pusher": {
        "username": "scalingo-platform-scm",
        "email": "deploy-scm@scalingo.com",
        "id": "us-f1de35ea-6a6d-4a25-8414-e2b34f5f61af"
      },
      "links": {
        "output": "https://api-osc-fr1.scalingo.com/v1/apps/625e727461d7b2000e5a1752/deployments/024810a3-d92c-4a1b-8244-8f1ff41b9ea0/output"
      }
    },
    {
      "id": "74a7788a-9a96-4c57-a6d1-df77bc331a0d",
      "app_id": "625e727461d7b2000e5a1752",
      "created_at": "2022-06-02T08:12:45.054Z",
      "finished_at": "2022-06-02T08:19:46.910+00:00",
      "status": "success",
      "git_ref": "3ca80caad827b3813f5e582c9ba38908bd7f4887",
      "previous_git_ref": "bee56032444be172c76bb07124c3cc1dde0b4aef",
      "type": "auto-deploy",
      "image": "registry-3-osc-fr1.scalingo.com/app-helios:3ca80caad827b38-74a7788a-9a96-4",
      "registry": "registry-3-osc-fr1.scalingo.com",
      "postdeploy_hook": "",
      "duration": 421,
      "pusher": {
        "username": "scalingo-platform-scm",
        "email": "deploy-scm@scalingo.com",
        "id": "us-f1de35ea-6a6d-4a25-8414-e2b34f5f61af"
      },
      "links": {
        "output": "https://api-osc-fr1.scalingo.com/v1/apps/625e727461d7b2000e5a1752/deployments/74a7788a-9a96-4c57-a6d1-df77bc331a0d/output"
      }
    },
    {
      "id": "98e4c97b-b938-4023-95b7-db5372ff89c7",
      "app_id": "625e727461d7b2000e5a1752",
      "created_at": "2022-05-31T15:18:29.218Z",
      "finished_at": "2022-05-31T15:28:54.295+00:00",
      "status": "success",
      "git_ref": "bee56032444be172c76bb07124c3cc1dde0b4aef",
      "previous_git_ref": "099166c2c54b6c0789bc155f6b4d9068c48dbc26",
      "type": "auto-deploy",
      "image": "registry-3-osc-fr1.scalingo.com/app-helios:bee56032444be17-98e4c97b-b938-4",
      "registry": "registry-3-osc-fr1.scalingo.com",
      "postdeploy_hook": "",
      "duration": 529,
      "pusher": {
        "username": "scalingo-platform-scm",
        "email": "deploy-scm@scalingo.com",
        "id": "us-f1de35ea-6a6d-4a25-8414-e2b34f5f61af"
      },
      "links": {
        "output": "https://api-osc-fr1.scalingo.com/v1/apps/625e727461d7b2000e5a1752/deployments/98e4c97b-b938-4023-95b7-db5372ff89c7/output"
      }
    },
    {
      "id": "e71db0c3-53ba-4548-a4d0-1639739a9e89",
      "app_id": "625e727461d7b2000e5a1752",
      "created_at": "2022-05-31T15:17:30.558Z",
      "finished_at": "2022-05-31T15:27:36.086+00:00",
      "status": "success",
      "git_ref": "099166c2c54b6c0789bc155f6b4d9068c48dbc26",
      "previous_git_ref": "b3c7f90532308389e359778d5111a0ee706612ac",
      "type": "auto-deploy",
      "image": "registry-3-osc-fr1.scalingo.com/app-helios:099166c2c54b6c0-e71db0c3-53ba-4",
      "registry": "registry-3-osc-fr1.scalingo.com",
      "postdeploy_hook": "",
      "duration": 490,
      "pusher": {
        "username": "scalingo-platform-scm",
        "email": "deploy-scm@scalingo.com",
        "id": "us-f1de35ea-6a6d-4a25-8414-e2b34f5f61af"
      },
      "links": {
        "output": "https://api-osc-fr1.scalingo.com/v1/apps/625e727461d7b2000e5a1752/deployments/e71db0c3-53ba-4548-a4d0-1639739a9e89/output"
      }
    },
    {
      "id": "aaadc583-56eb-4159-9673-c6a16abf103f",
      "app_id": "625e727461d7b2000e5a1752",
      "created_at": "2022-05-31T10:16:51.623Z",
      "finished_at": "2022-05-31T10:23:47.094+00:00",
      "status": "success",
      "git_ref": "b3c7f90532308389e359778d5111a0ee706612ac",
      "previous_git_ref": "cd2dac66a3afa34bea4f269a23ee4d59a24b6272",
      "type": "auto-deploy",
      "image": "registry-3-osc-fr1.scalingo.com/app-helios:b3c7f9053230838-aaadc583-56eb-4",
      "registry": "registry-3-osc-fr1.scalingo.com",
      "postdeploy_hook": "",
      "duration": 415,
      "pusher": {
        "username": "scalingo-platform-scm",
        "email": "deploy-scm@scalingo.com",
        "id": "us-f1de35ea-6a6d-4a25-8414-e2b34f5f61af"
      },
      "links": {
        "output": "https://api-osc-fr1.scalingo.com/v1/apps/625e727461d7b2000e5a1752/deployments/aaadc583-56eb-4159-9673-c6a16abf103f/output"
      }
    },
    {
      "id": "3c22557e-4906-4de8-9c7b-949fc2fcf5a6",
      "app_id": "625e727461d7b2000e5a1752",
      "created_at": "2022-05-31T09:36:44.871Z",
      "finished_at": "2022-05-31T09:43:55.175+00:00",
      "status": "success",
      "git_ref": "cd2dac66a3afa34bea4f269a23ee4d59a24b6272",
      "previous_git_ref": "8be4a88b03a61b1439c6d634694a0f9af08b83e2",
      "type": "auto-deploy",
      "image": "registry-3-osc-fr1.scalingo.com/app-helios:cd2dac66a3afa34-3c22557e-4906-4",
      "registry": "registry-3-osc-fr1.scalingo.com",
      "postdeploy_hook": "",
      "duration": 429,
      "pusher": {
        "username": "scalingo-platform-scm",
        "email": "deploy-scm@scalingo.com",
        "id": "us-f1de35ea-6a6d-4a25-8414-e2b34f5f61af"
      },
      "links": {
        "output": "https://api-osc-fr1.scalingo.com/v1/apps/625e727461d7b2000e5a1752/deployments/3c22557e-4906-4de8-9c7b-949fc2fcf5a6/output"
      }
    },
    {
      "id": "4fcb19cc-fdc7-4264-b6fa-c33cba89efb4",
      "app_id": "625e727461d7b2000e5a1752",
      "created_at": "2022-05-24T15:49:41.353Z",
      "finished_at": "2022-05-24T15:56:41.391+00:00",
      "status": "success",
      "git_ref": "8be4a88b03a61b1439c6d634694a0f9af08b83e2",
      "previous_git_ref": "bcfba719220c40e28455e7145527f42de31320f5",
      "type": "auto-deploy",
      "image": "registry-3-osc-fr1.scalingo.com/app-helios:8be4a88b03a61b1-4fcb19cc-fdc7-4",
      "registry": "registry-3-osc-fr1.scalingo.com",
      "postdeploy_hook": "",
      "duration": 419,
      "pusher": {
        "username": "scalingo-platform-scm",
        "email": "deploy-scm@scalingo.com",
        "id": "us-f1de35ea-6a6d-4a25-8414-e2b34f5f61af"
      },
      "links": {
        "output": "https://api-osc-fr1.scalingo.com/v1/apps/625e727461d7b2000e5a1752/deployments/4fcb19cc-fdc7-4264-b6fa-c33cba89efb4/output"
      }
    },
    {
      "id": "0b84143c-956e-42a0-a914-eddf36bcb240",
      "app_id": "625e727461d7b2000e5a1752",
      "created_at": "2022-05-20T09:44:50.991Z",
      "finished_at": "2022-05-20T09:51:13.558+00:00",
      "status": "success",
      "git_ref": "bcfba719220c40e28455e7145527f42de31320f5",
      "previous_git_ref": "d81fcc544f1c5ffbf43ceaa138aea1a015e6d7ab",
      "type": "auto-deploy",
      "image": "registry-3-osc-fr1.scalingo.com/app-helios:bcfba719220c40e-0b84143c-956e-4",
      "registry": "registry-3-osc-fr1.scalingo.com",
      "postdeploy_hook": "",
      "duration": 382,
      "pusher": {
        "username": "scalingo-platform-scm",
        "email": "deploy-scm@scalingo.com",
        "id": "us-f1de35ea-6a6d-4a25-8414-e2b34f5f61af"
      },
      "links": {
        "output": "https://api-osc-fr1.scalingo.com/v1/apps/625e727461d7b2000e5a1752/deployments/0b84143c-956e-42a0-a914-eddf36bcb240/output"
      }
    },
    {
      "id": "34a62797-5033-4324-a619-a936fa04f2a7",
      "app_id": "625e727461d7b2000e5a1752",
      "created_at": "2022-05-19T12:25:21.448Z",
      "finished_at": "2022-05-19T12:33:29.341+00:00",
      "status": "success",
      "git_ref": "d81fcc544f1c5ffbf43ceaa138aea1a015e6d7ab",
      "previous_git_ref": "05e78c55a3b8bb1dc5b22baca8176484d8bd6a34",
      "type": "auto-deploy",
      "image": "registry-3-osc-fr1.scalingo.com/app-helios:d81fcc544f1c5ff-34a62797-5033-4",
      "registry": "registry-3-osc-fr1.scalingo.com",
      "postdeploy_hook": "",
      "duration": 487,
      "pusher": {
        "username": "scalingo-platform-scm",
        "email": "deploy-scm@scalingo.com",
        "id": "us-f1de35ea-6a6d-4a25-8414-e2b34f5f61af"
      },
      "links": {
        "output": "https://api-osc-fr1.scalingo.com/v1/apps/625e727461d7b2000e5a1752/deployments/34a62797-5033-4324-a619-a936fa04f2a7/output"
      }
    },
    {
      "id": "9afb19cd-51bf-4fd4-9e9e-c40e9ac3abc5",
      "app_id": "625e727461d7b2000e5a1752",
      "created_at": "2022-05-17T16:55:35.429Z",
      "finished_at": "2022-05-17T17:00:22.334+00:00",
      "status": "success",
      "git_ref": "05e78c55a3b8bb1dc5b22baca8176484d8bd6a34",
      "previous_git_ref": "05e78c55a3b8bb1dc5b22baca8176484d8bd6a34",
      "type": "manual-deploy",
      "image": "registry-3-osc-fr1.scalingo.com/app-helios:05e78c55a3b8bb1-9afb19cd-51bf-4",
      "registry": "registry-3-osc-fr1.scalingo.com",
      "postdeploy_hook": "",
      "duration": 286,
      "pusher": {
        "username": "thierryg",
        "email": "thierry.gonard@octo.com",
        "id": "us-1eb8e5d1-926b-4252-a45e-854f48c70629"
      },
      "links": {
        "output": "https://api-osc-fr1.scalingo.com/v1/apps/625e727461d7b2000e5a1752/deployments/9afb19cd-51bf-4fd4-9e9e-c40e9ac3abc5/output"
      }
    },
    {
      "id": "6468e345-98dd-459e-9d75-7e0317be21a8",
      "app_id": "625e727461d7b2000e5a1752",
      "created_at": "2022-05-17T16:49:09.632Z",
      "finished_at": "2022-05-17T16:54:16.126+00:00",
      "status": "success",
      "git_ref": "05e78c55a3b8bb1dc5b22baca8176484d8bd6a34",
      "previous_git_ref": "01326d4ee4fc6f4742bd273d81abebf188476eaa",
      "type": "auto-deploy",
      "image": "registry-3-osc-fr1.scalingo.com/app-helios:05e78c55a3b8bb1-6468e345-98dd-4",
      "registry": "registry-3-osc-fr1.scalingo.com",
      "postdeploy_hook": "",
      "duration": 306,
      "pusher": {
        "username": "scalingo-platform-scm",
        "email": "deploy-scm@scalingo.com",
        "id": "us-f1de35ea-6a6d-4a25-8414-e2b34f5f61af"
      },
      "links": {
        "output": "https://api-osc-fr1.scalingo.com/v1/apps/625e727461d7b2000e5a1752/deployments/6468e345-98dd-459e-9d75-7e0317be21a8/output"
      }
    },
    {
      "id": "52fb56bb-8000-4c28-8662-8d5fef24fd81",
      "app_id": "625e727461d7b2000e5a1752",
      "created_at": "2022-05-11T15:44:12.666Z",
      "finished_at": "2022-05-11T15:49:31.735+00:00",
      "status": "success",
      "git_ref": "01326d4ee4fc6f4742bd273d81abebf188476eaa",
      "previous_git_ref": "01326d4ee4fc6f4742bd273d81abebf188476eaa",
      "type": "manual-deploy",
      "image": "registry-3-osc-fr1.scalingo.com/app-helios:01326d4ee4fc6f4-52fb56bb-8000-4",
      "registry": "registry-3-osc-fr1.scalingo.com",
      "postdeploy_hook": "",
      "duration": 318,
      "pusher": {
        "username": "thierryg",
        "email": "thierry.gonard@octo.com",
        "id": "us-1eb8e5d1-926b-4252-a45e-854f48c70629"
      },
      "links": {
        "output": "https://api-osc-fr1.scalingo.com/v1/apps/625e727461d7b2000e5a1752/deployments/52fb56bb-8000-4c28-8662-8d5fef24fd81/output"
      }
    },
    {
      "id": "54585666-9de0-49e5-94a1-d7adbcc1138b",
      "app_id": "625e727461d7b2000e5a1752",
      "created_at": "2022-05-11T15:37:23.223Z",
      "finished_at": "2022-05-11T15:42:21.445+00:00",
      "status": "hook-error",
      "git_ref": "01326d4ee4fc6f4742bd273d81abebf188476eaa",
      "previous_git_ref": "29273c531dafab3fc77e5b8d885ea4c5f6297340",
      "type": "auto-deploy",
      "image": "registry-3-osc-fr1.scalingo.com/app-helios:01326d4ee4fc6f4-54585666-9de0-4",
      "registry": "registry-3-osc-fr1.scalingo.com",
      "postdeploy_hook": "",
      "duration": 274,
      "pusher": {
        "username": "scalingo-platform-scm",
        "email": "deploy-scm@scalingo.com",
        "id": "us-f1de35ea-6a6d-4a25-8414-e2b34f5f61af"
      },
      "links": {
        "output": "https://api-osc-fr1.scalingo.com/v1/apps/625e727461d7b2000e5a1752/deployments/54585666-9de0-49e5-94a1-d7adbcc1138b/output"
      }
    },
    {
      "id": "233f5ef5-4cef-43d4-ac5d-24d9a81f1d8b",
      "app_id": "625e727461d7b2000e5a1752",
      "created_at": "2022-05-09T15:10:40.187Z",
      "finished_at": "2022-05-09T15:17:09.950+00:00",
      "status": "success",
      "git_ref": "29273c531dafab3fc77e5b8d885ea4c5f6297340",
      "previous_git_ref": "15429e62fe623dd1dbfcf79c7d0fd57ef3940a16",
      "type": "auto-deploy",
      "image": "registry-3-osc-fr1.scalingo.com/app-helios:29273c531dafab3-233f5ef5-4cef-4",
      "registry": "registry-3-osc-fr1.scalingo.com",
      "postdeploy_hook": "",
      "duration": 389,
      "pusher": {
        "username": "scalingo-platform-scm",
        "email": "deploy-scm@scalingo.com",
        "id": "us-f1de35ea-6a6d-4a25-8414-e2b34f5f61af"
      },
      "links": {
        "output": "https://api-osc-fr1.scalingo.com/v1/apps/625e727461d7b2000e5a1752/deployments/233f5ef5-4cef-43d4-ac5d-24d9a81f1d8b/output"
      }
    },
    {
      "id": "fefdfda7-0bae-4533-bf7a-b4cfc85a99e1",
      "app_id": "625e727461d7b2000e5a1752",
      "created_at": "2022-05-09T08:28:23.039Z",
      "finished_at": "2022-05-09T08:34:08.150+00:00",
      "status": "success",
      "git_ref": "15429e62fe623dd1dbfcf79c7d0fd57ef3940a16",
      "previous_git_ref": "dd506f137f2714eb296ad0823cf609029d02d48a",
      "type": "auto-deploy",
      "image": "registry-3-osc-fr1.scalingo.com/app-helios:15429e62fe623dd-fefdfda7-0bae-4",
      "registry": "registry-3-osc-fr1.scalingo.com",
      "postdeploy_hook": "",
      "duration": 344,
      "pusher": {
        "username": "scalingo-platform-scm",
        "email": "deploy-scm@scalingo.com",
        "id": "us-f1de35ea-6a6d-4a25-8414-e2b34f5f61af"
      },
      "links": {
        "output": "https://api-osc-fr1.scalingo.com/v1/apps/625e727461d7b2000e5a1752/deployments/fefdfda7-0bae-4533-bf7a-b4cfc85a99e1/output"
      }
    },
    {
      "id": "0f8ecf1d-248d-430d-8900-6e940ef74c57",
      "app_id": "625e727461d7b2000e5a1752",
      "created_at": "2022-05-06T12:41:27.905Z",
      "finished_at": "2022-05-06T12:44:55.229+00:00",
      "status": "success",
      "git_ref": "dd506f137f2714eb296ad0823cf609029d02d48a",
      "previous_git_ref": "6d58828e182254bc96d9dc4eadd018bd34f0973d",
      "type": "auto-deploy",
      "image": "registry-3-osc-fr1.scalingo.com/app-helios:dd506f137f2714e-0f8ecf1d-248d-4",
      "registry": "registry-3-osc-fr1.scalingo.com",
      "postdeploy_hook": "",
      "duration": 206,
      "pusher": {
        "username": "scalingo-platform-scm",
        "email": "deploy-scm@scalingo.com",
        "id": "us-f1de35ea-6a6d-4a25-8414-e2b34f5f61af"
      },
      "links": {
        "output": "https://api-osc-fr1.scalingo.com/v1/apps/625e727461d7b2000e5a1752/deployments/0f8ecf1d-248d-430d-8900-6e940ef74c57/output"
      }
    },
    {
      "id": "605b8ddc-a534-4b8c-bebe-f0c53a29769e",
      "app_id": "625e727461d7b2000e5a1752",
      "created_at": "2022-05-02T13:27:06.732Z",
      "finished_at": "2022-05-02T13:32:14.769+00:00",
      "status": "success",
      "git_ref": "6d58828e182254bc96d9dc4eadd018bd34f0973d",
      "previous_git_ref": "62d36695c82bc0b62b0b47b9af55d630f19cfb37",
      "type": "auto-deploy",
      "image": "registry-3-osc-fr1.scalingo.com/app-helios:6d58828e182254b-605b8ddc-a534-4",
      "registry": "registry-3-osc-fr1.scalingo.com",
      "postdeploy_hook": "",
      "duration": 307,
      "pusher": {
        "username": "scalingo-platform-scm",
        "email": "deploy-scm@scalingo.com",
        "id": "us-f1de35ea-6a6d-4a25-8414-e2b34f5f61af"
      },
      "links": {
        "output": "https://api-osc-fr1.scalingo.com/v1/apps/625e727461d7b2000e5a1752/deployments/605b8ddc-a534-4b8c-bebe-f0c53a29769e/output"
      }
    },
    {
      "id": "aef56a99-60b4-4bfa-820d-17773f7c7a3f",
      "app_id": "625e727461d7b2000e5a1752",
      "created_at": "2022-04-28T08:58:59.990Z",
      "finished_at": "2022-04-28T09:02:24.073+00:00",
      "status": "success",
      "git_ref": "62d36695c82bc0b62b0b47b9af55d630f19cfb37",
      "previous_git_ref": "29055529b5635ca1d29948aad2d29464efb3688e",
      "type": "auto-deploy",
      "image": "registry-3-osc-fr1.scalingo.com/app-helios:62d36695c82bc0b-aef56a99-60b4-4",
      "registry": "registry-3-osc-fr1.scalingo.com",
      "postdeploy_hook": "",
      "duration": 203,
      "pusher": {
        "username": "scalingo-platform-scm",
        "email": "deploy-scm@scalingo.com",
        "id": "us-f1de35ea-6a6d-4a25-8414-e2b34f5f61af"
      },
      "links": {
        "output": "https://api-osc-fr1.scalingo.com/v1/apps/625e727461d7b2000e5a1752/deployments/aef56a99-60b4-4bfa-820d-17773f7c7a3f/output"
      }
    },
    {
      "id": "23020cc2-7264-461c-98bb-1f680e837034",
      "app_id": "625e727461d7b2000e5a1752",
      "created_at": "2022-04-28T06:38:54.626Z",
      "finished_at": "2022-04-28T06:42:14.376+00:00",
      "status": "success",
      "git_ref": "29055529b5635ca1d29948aad2d29464efb3688e",
      "previous_git_ref": "805f9fa2796b7745bdae40f0a0e84f7cfd0afcbb",
      "type": "auto-deploy",
      "image": "registry-3-osc-fr1.scalingo.com/app-helios:29055529b5635ca-23020cc2-7264-4",
      "registry": "registry-3-osc-fr1.scalingo.com",
      "postdeploy_hook": "",
      "duration": 198,
      "pusher": {
        "username": "scalingo-platform-scm",
        "email": "deploy-scm@scalingo.com",
        "id": "us-f1de35ea-6a6d-4a25-8414-e2b34f5f61af"
      },
      "links": {
        "output": "https://api-osc-fr1.scalingo.com/v1/apps/625e727461d7b2000e5a1752/deployments/23020cc2-7264-461c-98bb-1f680e837034/output"
      }
    },
    {
      "id": "dc5af445-1131-46cc-8b28-2db144a332c2",
      "app_id": "625e727461d7b2000e5a1752",
      "created_at": "2022-04-26T16:31:51.923Z",
      "finished_at": "2022-04-26T16:36:23.586+00:00",
      "status": "success",
      "git_ref": "805f9fa2796b7745bdae40f0a0e84f7cfd0afcbb",
      "previous_git_ref": "805f9fa2796b7745bdae40f0a0e84f7cfd0afcbb",
      "type": "manual-deploy",
      "image": "registry-3-osc-fr1.scalingo.com/app-helios:805f9fa2796b774-dc5af445-1131-4",
      "registry": "registry-3-osc-fr1.scalingo.com",
      "postdeploy_hook": "",
      "duration": 271,
      "pusher": {
        "username": "thierryg",
        "email": "thierry.gonard@octo.com",
        "id": "us-1eb8e5d1-926b-4252-a45e-854f48c70629"
      },
      "links": {
        "output": "https://api-osc-fr1.scalingo.com/v1/apps/625e727461d7b2000e5a1752/deployments/dc5af445-1131-46cc-8b28-2db144a332c2/output"
      }
    },
    {
      "id": "c0856a55-d017-436b-a435-14ec13891be9",
      "app_id": "625e727461d7b2000e5a1752",
      "created_at": "2022-04-26T16:27:42.211Z",
      "finished_at": "2022-04-26T16:29:41.142+00:00",
      "status": "build-error",
      "git_ref": "805f9fa2796b7745bdae40f0a0e84f7cfd0afcbb",
      "previous_git_ref": "e53f861290636e5ddb8fe11799d5db5802f24c4a",
      "type": "auto-deploy",
      "image": null,
      "registry": "registry-3-osc-fr1.scalingo.com",
      "postdeploy_hook": "",
      "duration": 0,
      "pusher": {
        "username": "scalingo-platform-scm",
        "email": "deploy-scm@scalingo.com",
        "id": "us-f1de35ea-6a6d-4a25-8414-e2b34f5f61af"
      },
      "links": {
        "output": "https://api-osc-fr1.scalingo.com/v1/apps/625e727461d7b2000e5a1752/deployments/c0856a55-d017-436b-a435-14ec13891be9/output"
      }
    },
    {
      "id": "96bef80b-bbd1-4bce-ac7b-04c66e49d960",
      "app_id": "625e727461d7b2000e5a1752",
      "created_at": "2022-04-25T09:20:43.873Z",
      "finished_at": "2022-04-25T09:24:51.168+00:00",
      "status": "success",
      "git_ref": "e53f861290636e5ddb8fe11799d5db5802f24c4a",
      "previous_git_ref": "c97cab926f1e0c303fcb922a1b843a6d6221634d",
      "type": "auto-deploy",
      "image": "registry-3-osc-fr1.scalingo.com/app-helios:e53f861290636e5-96bef80b-bbd1-4",
      "registry": "registry-3-osc-fr1.scalingo.com",
      "postdeploy_hook": "",
      "duration": 246,
      "pusher": {
        "username": "scalingo-platform-scm",
        "email": "deploy-scm@scalingo.com",
        "id": "us-f1de35ea-6a6d-4a25-8414-e2b34f5f61af"
      },
      "links": {
        "output": "https://api-osc-fr1.scalingo.com/v1/apps/625e727461d7b2000e5a1752/deployments/96bef80b-bbd1-4bce-ac7b-04c66e49d960/output"
      }
    },
    {
      "id": "cf283aa0-9122-4bb0-91a0-fd535cf57e4e",
      "app_id": "625e727461d7b2000e5a1752",
      "created_at": "2022-04-22T16:06:07.301Z",
      "finished_at": "2022-04-22T16:09:11.253+00:00",
      "status": "success",
      "git_ref": "c97cab926f1e0c303fcb922a1b843a6d6221634d",
      "previous_git_ref": "02a934b3864214a597c967a55092bbc045e9a504",
      "type": "auto-deploy",
      "image": "registry-3-osc-fr1.scalingo.com/app-helios:c97cab926f1e0c3-cf283aa0-9122-4",
      "registry": "registry-3-osc-fr1.scalingo.com",
      "postdeploy_hook": "",
      "duration": 183,
      "pusher": {
        "username": "scalingo-platform-scm",
        "email": "deploy-scm@scalingo.com",
        "id": "us-f1de35ea-6a6d-4a25-8414-e2b34f5f61af"
      },
      "links": {
        "output": "https://api-osc-fr1.scalingo.com/v1/apps/625e727461d7b2000e5a1752/deployments/cf283aa0-9122-4bb0-91a0-fd535cf57e4e/output"
      }
    },
    {
      "id": "e194b5d7-ade4-4e82-88f2-720cb3a48fea",
      "app_id": "625e727461d7b2000e5a1752",
      "created_at": "2022-04-22T14:08:16.065Z",
      "finished_at": "2022-04-22T14:11:50.004+00:00",
      "status": "success",
      "git_ref": "02a934b3864214a597c967a55092bbc045e9a504",
      "previous_git_ref": "4d9e1d1086c8413cd764c8f9d279fac7f61204db",
      "type": "auto-deploy",
      "image": "registry-3-osc-fr1.scalingo.com/app-helios:02a934b3864214a-e194b5d7-ade4-4",
      "registry": "registry-3-osc-fr1.scalingo.com",
      "postdeploy_hook": "",
      "duration": 213,
      "pusher": {
        "username": "scalingo-platform-scm",
        "email": "deploy-scm@scalingo.com",
        "id": "us-f1de35ea-6a6d-4a25-8414-e2b34f5f61af"
      },
      "links": {
        "output": "https://api-osc-fr1.scalingo.com/v1/apps/625e727461d7b2000e5a1752/deployments/e194b5d7-ade4-4e82-88f2-720cb3a48fea/output"
      }
    },
    {
      "id": "9334d628-c8a3-4ccb-8e51-33dc8355d4ee",
      "app_id": "625e727461d7b2000e5a1752",
      "created_at": "2022-04-21T08:09:47.128Z",
      "finished_at": "2022-04-21T08:14:57.970+00:00",
      "status": "success",
      "git_ref": "4d9e1d1086c8413cd764c8f9d279fac7f61204db",
      "previous_git_ref": "b214107dccb9088348165a97c83f8760a261a5a0",
      "type": "auto-deploy",
      "image": "registry-3-osc-fr1.scalingo.com/app-helios:4d9e1d1086c8413-9334d628-c8a3-4",
      "registry": "registry-3-osc-fr1.scalingo.com",
      "postdeploy_hook": "",
      "duration": 310,
      "pusher": {
        "username": "scalingo-platform-scm",
        "email": "deploy-scm@scalingo.com",
        "id": "us-f1de35ea-6a6d-4a25-8414-e2b34f5f61af"
      },
      "links": {
        "output": "https://api-osc-fr1.scalingo.com/v1/apps/625e727461d7b2000e5a1752/deployments/9334d628-c8a3-4ccb-8e51-33dc8355d4ee/output"
      }
    },
    {
      "id": "2f666e18-9ffd-49b5-8bb8-4f7e6534ab8e",
      "app_id": "625e727461d7b2000e5a1752",
      "created_at": "2022-04-20T09:22:21.131Z",
      "finished_at": "2022-04-20T09:25:38.542+00:00",
      "status": "success",
      "git_ref": "b214107dccb9088348165a97c83f8760a261a5a0",
      "previous_git_ref": "076bafef81cc8edb06de8b378834477f329f159c",
      "type": "auto-deploy",
      "image": "registry-3-osc-fr1.scalingo.com/app-helios:b214107dccb9088-2f666e18-9ffd-4",
      "registry": "registry-3-osc-fr1.scalingo.com",
      "postdeploy_hook": "",
      "duration": 197,
      "pusher": {
        "username": "scalingo-platform-scm",
        "email": "deploy-scm@scalingo.com",
        "id": "us-f1de35ea-6a6d-4a25-8414-e2b34f5f61af"
      },
      "links": {
        "output": "https://api-osc-fr1.scalingo.com/v1/apps/625e727461d7b2000e5a1752/deployments/2f666e18-9ffd-49b5-8bb8-4f7e6534ab8e/output"
      }
    },
    {
      "id": "90386e19-0ce6-4b00-bb4f-2fde2920bf6f",
      "app_id": "625e727461d7b2000e5a1752",
      "created_at": "2022-04-19T12:57:30.181Z",
      "finished_at": "2022-04-19T13:00:09.298+00:00",
      "status": "success",
      "git_ref": "076bafef81cc8edb06de8b378834477f329f159c",
      "previous_git_ref": "20ed1425143c15d3d353ff6fa1b8c994673e5a67",
      "type": "auto-deploy",
      "image": "registry-3-osc-fr1.scalingo.com/app-helios:076bafef81cc8ed-90386e19-0ce6-4",
      "registry": "registry-3-osc-fr1.scalingo.com",
      "postdeploy_hook": "",
      "duration": 158,
      "pusher": {
        "username": "scalingo-platform-scm",
        "email": "deploy-scm@scalingo.com",
        "id": "us-f1de35ea-6a6d-4a25-8414-e2b34f5f61af"
      },
      "links": {
        "output": "https://api-osc-fr1.scalingo.com/v1/apps/625e727461d7b2000e5a1752/deployments/90386e19-0ce6-4b00-bb4f-2fde2920bf6f/output"
      }
    },
    {
      "id": "f7ba8dd4-4e5c-46f5-8ab5-93483752eb1c",
      "app_id": "625e727461d7b2000e5a1752",
      "created_at": "2022-04-19T12:26:53.566Z",
      "finished_at": "2022-04-19T12:29:07.426+00:00",
      "status": "build-error",
      "git_ref": "20ed1425143c15d3d353ff6fa1b8c994673e5a67",
      "previous_git_ref": "eff387499b758c2917e7746f3fd10712d7203bbe",
      "type": "manual-deploy",
      "image": null,
      "registry": "registry-3-osc-fr1.scalingo.com",
      "postdeploy_hook": "",
      "duration": 0,
      "pusher": {
        "username": "thierryg",
        "email": "thierry.gonard@octo.com",
        "id": "us-1eb8e5d1-926b-4252-a45e-854f48c70629"
      },
      "links": {
        "output": "https://api-osc-fr1.scalingo.com/v1/apps/625e727461d7b2000e5a1752/deployments/f7ba8dd4-4e5c-46f5-8ab5-93483752eb1c/output"
      }
    },
    {
      "id": "6979f7e1-2cc5-403a-a289-613326e491ea",
      "app_id": "625e727461d7b2000e5a1752",
      "created_at": "2022-04-19T08:37:13.841Z",
      "finished_at": "2022-04-19T08:40:15.651+00:00",
      "status": "success",
      "git_ref": "eff387499b758c2917e7746f3fd10712d7203bbe",
      "previous_git_ref": "20ed1425143c15d3d353ff6fa1b8c994673e5a67",
      "type": "manual-deploy",
      "image": "registry-3-osc-fr1.scalingo.com/app-helios:eff387499b758c2-6979f7e1-2cc5-4",
      "registry": "registry-3-osc-fr1.scalingo.com",
      "postdeploy_hook": "",
      "duration": 181,
      "pusher": {
        "username": "thierryg",
        "email": "thierry.gonard@octo.com",
        "id": "us-1eb8e5d1-926b-4252-a45e-854f48c70629"
      },
      "links": {
        "output": "https://api-osc-fr1.scalingo.com/v1/apps/625e727461d7b2000e5a1752/deployments/6979f7e1-2cc5-403a-a289-613326e491ea/output"
      }
    },
    {
      "id": "a415210d-43c7-4cb6-aa54-5f74fa517f93",
      "app_id": "625e727461d7b2000e5a1752",
      "created_at": "2022-04-19T08:35:15.105Z",
      "finished_at": "2022-04-19T08:36:09.821+00:00",
      "status": "build-error",
      "git_ref": "20ed1425143c15d3d353ff6fa1b8c994673e5a67",
      "previous_git_ref": null,
      "type": "manual-deploy",
      "image": null,
      "registry": "registry-3-osc-fr1.scalingo.com",
      "postdeploy_hook": "",
      "duration": 0,
      "pusher": {
        "username": "thierryg",
        "email": "thierry.gonard@octo.com",
        "id": "us-1eb8e5d1-926b-4252-a45e-854f48c70629"
      },
      "links": {
        "output": "https://api-osc-fr1.scalingo.com/v1/apps/625e727461d7b2000e5a1752/deployments/a415210d-43c7-4cb6-aa54-5f74fa517f93/output"
      }
    }
  ]
}